{
    "tokens": {
        "primary": "#c8102e",
        "background": "#0b3d23",
        "surface": "#f6f3ec",
        "text": "#1a1a1a",
        "muted": "#5a5a5a",
        "error": "#b00020",
        "radius": "12px",
        "fontFamily": "'Georgia', 'Times New Roman', serif"
    },
    "logoUrl": null,
    "title": "Buone Feste!",
    "intro": "Un piccolo sondaggio prima delle vacanze.",
    "closingMessage": "Grazie e tanti auguri! 🎄",
    "labels": {
        "next": "Avanti",
        "back": "Indietro",
        "submit": "Invia"
    },
    "layout": {
        "showProgressBar": true,
        "onePerScreen": true
    }
}
